wsgioauth2.py
wsgi_oauth2-0.2.2.dist-info/LICENSE
wsgi_oauth2-0.2.2.dist-info/METADATA
wsgi_oauth2-0.2.2.dist-info/WHEEL
wsgi_oauth2-0.2.2.dist-info/top_level.txt
wsgi_oauth2-0.2.2.dist-info/RECORD
