Metadata-Version: 2.1
Name: wsgi-oauth2
Version: 0.2.2
Summary: Simple WSGI middleware for OAuth 2.0
Home-page: https://dahlia.github.io/wsgi-oauth2/
Author: Hong Minhee
Author-email: hong.minhee@gmail.com
License: MIT license
Platform: UNKNOWN
Classifier: Development Status :: 5 - Production/Stable
Classifier: Environment :: Web Environment
Classifier: Intended Audience :: Developers
Classifier: Intended Audience :: System Administrators
Classifier: License :: OSI Approved :: MIT License
Classifier: Programming Language :: Python :: 2.6
Classifier: Programming Language :: Python :: 2.7
Classifier: Programming Language :: Python :: 3
Classifier: Programming Language :: Python :: 3.2
Classifier: Programming Language :: Python :: 3.3
Classifier: Programming Language :: Python :: 3.4
Classifier: Programming Language :: Python :: 3.5
Classifier: Programming Language :: Python :: 3.6
Classifier: Programming Language :: Python :: 3.7
Classifier: Programming Language :: Python :: 3.8
Classifier: Topic :: Internet :: WWW/HTTP :: WSGI :: Middleware
Requires-Python: !=3.0.*,!=3.1.*,<4,>=2.6
